{"id":"tt0098833","pT":"Jeeves and Wooster","sY":1990,"rM":55,"eY":1993,"iA":0,"aR":8.4,"nV":13286,"g":["Comedy"],"sI":[1,2,3,4],"eI":[1,2,3,4,5,6],"eM":{"1":{"1":{"id":"tt0614722","pT":"In Court After the Boat Race (or, Jeeves' Arrival)","aR":8.1,"nV":466},"2":{"id":"tt0614716","pT":"Bertie Is in Love (or, Golf Tournament)","aR":8,"nV":367},"3":{"id":"tt0614732","pT":"The Village Sports Day at Twing (or, the Gambling Event)","aR":8.1,"nV":332},"4":{"id":"tt0614721","pT":"How Does Gussie Woo Madeline? (or, Hunger Strike)","aR":8,"nV":303},"5":{"id":"tt0614734","pT":"Will Anatole Return to Brinkley Court? (or, the Matchmaker)","aR":8.2,"nV":304}},"2":{"1":{"id":"tt0614726","pT":"The Silver Jug (or Jeeves Saves the Cow Creamer)","aR":8.3,"nV":283},"2":{"id":"tt0614728","pT":"The Bassetts' Fancy Dress Ball (or, A Plan for Gussie)","aR":8.2,"nV":262},"3":{"id":"tt0614729","pT":"The Con (or, Pearls Mean Tears)","aR":8.5,"nV":273},"4":{"id":"tt0614718","pT":"Chuffy (or, Jeeves in the Country)","aR":8.5,"nV":286},"5":{"id":"tt0614731","pT":"The Mysterious Stranger (or, Kidnapped)","aR":8.4,"nV":248},"6":{"id":"tt0614735","pT":"Wooster with a Wife (or, Jeeves the Matchmaker)","aR":8.1,"nV":243}},"3":{"1":{"id":"tt0614725","pT":"Safety in New York (or, Bertie Sets Sail)","aR":8.1,"nV":245},"2":{"id":"tt0614715","pT":"Bertie Ensures Bicky Can Continue to Live in Manhattan (or, the Full House)","aR":8.1,"nV":232},"3":{"id":"tt0614719","pT":"Cyril and the Broadway Musical (or, Introduction on Broadway)","aR":8.2,"nV":223},"4":{"id":"tt0614717","pT":"Bertie Takes Gussie's Place at Deverill Hall (or, Right Ho! Jeeves)","aR":8.3,"nV":222},"5":{"id":"tt0614727","pT":"Sir Watkyn Bassett's Memoirs (or, Hot Off the Press)","aR":8,"nV":207},"6":{"id":"tt0614714","pT":"Aunt Dahlia, Cornelia and Madeline (or, Comrade Bingo)","aR":8.2,"nV":206}},"4":{"1":{"id":"tt0614724","pT":"Return to New York","aR":8,"nV":211},"2":{"id":"tt0614723","pT":"Lady Florence Craye Arrives in New York (or, the Once and Future Ex)","aR":7.6,"nV":198},"3":{"id":"tt0614720","pT":"Honoria Glossop Turns Up (or, Bridegroom Wanted!)","aR":7.8,"nV":198},"4":{"id":"tt0614713","pT":"Arrested in a Night Club (or, the Delayed Arrival)","aR":7.9,"nV":191},"5":{"id":"tt0614733","pT":"Totleigh Towers (or, Trouble at Totleigh Towers)","aR":8.1,"nV":186},"6":{"id":"tt0614730","pT":"The Ex's Are Nearly Married Off (or, the Ties That Bind)","aR":8.5,"nV":225}}}}