{"id":"tt0159545","pT":"Her Ladyship the Judge (1978)","sY":1978,"nV":42,"rM":90,"eY":1978,"aR":7,"iA":false,"g":["Crime","Drama"],"sI":[1],"eI":[1,2,3,4,5,6],"eM":{"1":{"1":{"id":"tt0799489","pT":"Le dossier Françoise Muller","aR":6.9,"nV":11},"2":{"id":"tt0806891","pT":"Monsieur Bais","aR":6.9,"nV":9},"3":{"id":"tt1066816","pT":"Un innocent","aR":6.5,"nV":7},"4":{"id":"tt1066817","pT":"Le feu","aR":6.2,"nV":6},"5":{"id":"tt1066814","pT":"2 + 2 = 4","aR":5.8,"nV":11},"6":{"id":"tt1066815","pT":"Autopsie d'un témoignage","aR":6.6,"nV":6}}}}