{"id":"tt0172022","pT":"MA 2412","sY":1998,"nV":487,"rM":20,"eY":2022,"aR":7.7,"iA":false,"g":["Comedy"],"sI":[1,2,3,4],"eI":[1,2,3,4,5,6,7,8,9,10,11,12,22],"eM":{"1":{"1":{"id":"tt0952839","pT":"Der Akt","aR":8.2,"nV":12},"2":{"id":"tt0952840","pT":"Fasching","aR":8.4,"nV":12},"3":{"id":"tt0952841","pT":"Sucht","aR":8.6,"nV":12},"4":{"id":"tt1066382","pT":"Meisterschaft","aR":8.4,"nV":11},"5":{"id":"tt0638529","pT":"Lotto","aR":8.2,"nV":11},"6":{"id":"tt1068203","pT":"Sex","aR":8.2,"nV":10},"7":{"id":"tt1068199","pT":"Auto","aR":8.7,"nV":11},"8":{"id":"tt1068205","pT":"Urlaub","aR":8.2,"nV":10},"9":{"id":"tt1068201","pT":"Karriere","aR":7.9,"nV":11},"10":{"id":"tt1068204","pT":"Tribunal","aR":8.3,"nV":12},"11":{"id":"tt1068202","pT":"Liebe","aR":7.5,"nV":12},"12":{"id":"tt1068200","pT":"Horror","aR":7.6,"nV":12},"22":{"id":"tt1068983","pT":"Hollywood","aR":7.9,"nV":10}},"2":{"1":{"id":"tt1068695","pT":"Freud","aR":9,"nV":10},"2":{"id":"tt1066383","pT":"Verwandlung","aR":8.4,"nV":10},"3":{"id":"tt1068696","pT":"Kebab","aR":8.3,"nV":10},"4":{"id":"tt1068694","pT":"Der Vogel","aR":8.7,"nV":10},"5":{"id":"tt1068697","pT":"Körperkult","aR":8.1,"nV":10},"6":{"id":"tt1068698","pT":"Tag der offenen Tür","aR":8.2,"nV":10}},"3":{"1":{"id":"tt1068981","pT":"Außendienst","aR":8.1,"nV":10},"2":{"id":"tt0638527","pT":"Geiselnahme","aR":8.3,"nV":11},"3":{"id":"tt1068982","pT":"Gemüse im Netz","aR":8.2,"nV":10},"5":{"id":"tt1068987","pT":"Wissen ist Macht","aR":9.2,"nV":11},"6":{"id":"tt1066381","pT":"Der Neue","aR":8.1,"nV":11},"7":{"id":"tt1068984","pT":"Parkpickerl 1. Teil","aR":8.1,"nV":11},"8":{"id":"tt1068985","pT":"Parkpickerl 2. Teil","aR":8,"nV":9}},"4":{"1":{"id":"tt1070183","pT":"Weihnachten","aR":7.9,"nV":8},"2":{"id":"tt0638528","pT":"Geldrausch","aR":7.9,"nV":9},"3":{"id":"tt1068988","pT":"Zeitreise","aR":8,"nV":9},"4":{"id":"tt1068986","pT":"Wahlkampf","aR":7.9,"nV":8},"5":{"id":"tt1070180","pT":"Kontrolle","aR":8.1,"nV":9},"6":{"id":"tt1070182","pT":"Totalschaden","aR":7.8,"nV":7},"7":{"id":"tt1070181","pT":"Talkshow","aR":8.7,"nV":10},"8":{"id":"tt1070179","pT":"Das Ende","aR":8.8,"nV":11}}}}