{"id":"tt1082583","pT":"The Dangerous Book for Boys","sY":2018,"rM":30,"eY":2018,"iA":0,"aR":5.8,"nV":519,"g":["Adventure","Comedy","Drama"],"sI":[1],"eI":[1,2,3,4,5,6],"eM":{"1":{"1":{"id":"tt7136608","pT":"How to Walk on the Moon","aR":7.1,"nV":59},"2":{"id":"tt7222856","pT":"How to Play Poker","aR":7.3,"nV":38},"3":{"id":"tt7222858","pT":"How to Be an Explorer","aR":7.6,"nV":38},"4":{"id":"tt7222862","pT":"The Trojan War","aR":7.1,"nV":29},"5":{"id":"tt7222864","pT":"How to Talk to Girls","aR":7.5,"nV":32},"6":{"id":"tt7222866","pT":"How to Build a Treehouse","aR":7.2,"nV":33}}}}