{"id":"tt1354462","pT":"Pirunpelto","sY":2009,"nV":235,"rM":null,"eY":2013,"aR":7.3,"iA":false,"g":["Comedy","Drama"],"sI":[1,2,3,4],"eI":[1,2,3,4,5,6],"eM":{"1":{"1":{"id":"tt1368321","pT":"Kovan aamun päivä","aR":6.9,"nV":14},"2":{"id":"tt1368320","pT":"Kaikki sitä haluaa","aR":7.2,"nV":12},"3":{"id":"tt1368322","pT":"Kun kaikki kaatuu","aR":7.3,"nV":12},"4":{"id":"tt1368319","pT":"Jos ei tykätä ni tapetaan","aR":7.2,"nV":12},"5":{"id":"tt1374488","pT":"Tapahtumien yö","aR":7.5,"nV":11},"6":{"id":"tt1384468","pT":"Hengetön tietää","aR":7.9,"nV":12}},"2":{"1":{"id":"tt1853266","pT":"Vieraita ja vesivahinkoja","aR":7.4,"nV":12},"2":{"id":"tt1853267","pT":"Yllättävää yhteistyötä","aR":6.9,"nV":11},"3":{"id":"tt1853265","pT":"Soraa, seksiä ja sopimuksia","aR":6.9,"nV":9},"4":{"id":"tt1853263","pT":"Ahkerointia aamunkoitteessa","aR":7,"nV":9},"5":{"id":"tt1853268","pT":"Yöllisiä ystäviä","aR":7,"nV":9},"6":{"id":"tt1853264","pT":"Kohti kuilun reunaa","aR":7,"nV":9}},"3":{"1":{"id":"tt2566482","pT":"Tummanpuhuvia tunteita","aR":7.8,"nV":9},"2":{"id":"tt2566488","pT":"Tarkastaja törmäyskurssilla","aR":6.3,"nV":9},"3":{"id":"tt2580806","pT":"Vanhat velat: Uudet pelurit","aR":6.7,"nV":9},"4":{"id":"tt2580808","pT":"Tuuli tietää enemmän","aR":6.4,"nV":9},"5":{"id":"tt2580812","pT":"Hattukankaan hintasota","aR":6.6,"nV":8},"6":{"id":"tt2614422","pT":"Kun käteinen ei riitä","aR":6.6,"nV":8}},"4":{"1":{"id":"tt2636628","pT":"Rahaa ilman rakkautta","aR":7.6,"nV":8},"2":{"id":"tt2672250","pT":"Pelastavat enkelit","aR":7.1,"nV":8},"3":{"id":"tt2672260","pT":"Östelääkin ovelampi","aR":7.9,"nV":8},"4":{"id":"tt2700168","pT":"Uhka idästä","aR":7.8,"nV":8},"5":{"id":"tt2727088","pT":"Ilman epäröintiä","aR":7.8,"nV":8},"6":{"id":"tt2727090","pT":"Tilinpäätös Tyrisevän tapaan","aR":8.6,"nV":9}}}}