{"id":"tt13984270","pT":"The Thing About Pam","sY":2022,"rM":43,"eY":2022,"iA":0,"aR":7.2,"nV":11385,"g":["Comedy","Crime","Drama"],"sI":[1,2],"eI":[1,2,3,4,5,6],"eM":{"1":{"1":{"id":"tt14588486","pT":"She's a Good Friend","aR":7.2,"nV":470},"2":{"id":"tt15513376","pT":"She's a Helper","aR":7.4,"nV":349},"3":{"id":"tt16030412","pT":"She's a Star Witness","aR":7.7,"nV":342},"4":{"id":"tt16023286","pT":"She's a Loving Daughter","aR":7.7,"nV":337},"5":{"id":"tt16413926","pT":"She's Not Who You Think She Is","aR":7.6,"nV":290},"6":{"id":"tt16350242","pT":"She's a Killer","aR":7.9,"nV":292}},"2":{}}}