{"id":"tt15171996","pT":"Baking Impossible","sY":2021,"rM":null,"eY":2021,"iA":0,"aR":7,"nV":1530,"g":["Game-Show","Reality-TV"],"sI":[1],"eI":[1,2,3,4,5,6,7,8],"eM":{"1":{"1":{"id":"tt15491470","pT":"Whatever Floats Your Boat","aR":7.5,"nV":70},"2":{"id":"tt15561876","pT":"Off to the Robot Races","aR":7.5,"nV":64},"3":{"id":"tt15561878","pT":"Sweet Chain Reactions","aR":7.5,"nV":58},"4":{"id":"tt15561880","pT":"Fore! The Love of Mini Golf","aR":7.3,"nV":48},"5":{"id":"tt15561882","pT":"Cake on the Catwalk","aR":7.2,"nV":45},"6":{"id":"tt15561886","pT":"Baking to New Heights","aR":8.1,"nV":50},"7":{"id":"tt15561892","pT":"Crash Test Yummy","aR":7.6,"nV":41},"8":{"id":"tt15561894","pT":"Bridge to Victory","aR":6.4,"nV":52}}}}