{"id":"tt18257378","pT":"The Dynasty: New England Patriots","sY":2024,"rM":null,"eY":2024,"iA":0,"aR":8.3,"nV":1785,"g":["Documentary","Sport"],"sI":[1],"eI":[1,2,3,4,5,6,7,8,9,10],"eM":{"1":{"1":{"id":"tt30028009","pT":"Backup Plan","aR":8.9,"nV":173},"2":{"id":"tt30816764","pT":"The Snow Bowl","aR":8.8,"nV":166},"3":{"id":"tt30816770","pT":"Borrowed Time","aR":8.7,"nV":145},"4":{"id":"tt30816772","pT":"Spygate","aR":8.6,"nV":141},"5":{"id":"tt30816773","pT":"Torn","aR":8.2,"nV":124},"6":{"id":"tt30816777","pT":"At All Costs","aR":8.6,"nV":133},"7":{"id":"tt30816781","pT":"Under Pressure","aR":7.9,"nV":114},"8":{"id":"tt30816784","pT":"Score To Settle","aR":9,"nV":123},"9":{"id":"tt30816787","pT":"Breaking Point","aR":8.4,"nV":106},"10":{"id":"tt30816792","pT":"End Game","aR":8.7,"nV":96}}}}