{"id":"tt1981538","pT":"Kroll Show","sY":2013,"rM":30,"eY":2015,"iA":0,"aR":7,"nV":5358,"g":["Comedy"],"sI":[1,2,3],"eI":[0,1,2,3,4,5,6,7,8,9,10,11],"eM":{"1":{"1":{"id":"tt1998065","pT":"San Diego Diet","aR":7.3,"nV":135},"2":{"id":"tt2630024","pT":"Soaked in Success","aR":7.5,"nV":88},"3":{"id":"tt2630030","pT":"Secret Room","aR":7.6,"nV":77},"4":{"id":"tt2630032","pT":"Too Much Tuna","aR":7.6,"nV":85},"5":{"id":"tt2309695","pT":"Can I Finish?","aR":7.8,"nV":97},"6":{"id":"tt2630038","pT":"Dine & Dash","aR":7.5,"nV":63},"7":{"id":"tt2319521","pT":"Ice Dating","aR":7.3,"nV":66},"8":{"id":"tt2630044","pT":"Please God","aR":7.7,"nV":77}},"2":{"0":{"id":"tt3427862","pT":"The Greatest Hits of It","aR":7.9,"nV":30},"1":{"id":"tt3448036","pT":"Cake Train","aR":8.3,"nV":61},"2":{"id":"tt2998652","pT":"#canadiansafesex","aR":8.6,"nV":65},"3":{"id":"tt3448048","pT":"Oh Armond","aR":8.1,"nV":52},"4":{"id":"tt2903074","pT":"Sponsored by Stamps","aR":8.5,"nV":57},"5":{"id":"tt3495802","pT":"Krolling Around with Nick Klown","aR":8.1,"nV":59},"6":{"id":"tt3534080","pT":"Mother Daughter Sister Wife","aR":8.2,"nV":40},"7":{"id":"tt3558822","pT":"Finger Magnets","aR":8.2,"nV":45},"8":{"id":"tt3079496","pT":"Mercury Poisoning","aR":8.4,"nV":46},"9":{"id":"tt3590676","pT":"Bounce","aR":7.9,"nV":41},"10":{"id":"tt3603738","pT":"Banff Is on Fire","aR":7.6,"nV":45},"11":{"id":"tt3616070","pT":"Blisteritos Presents Dad Academy Graduation Congraduritos Red Carpet Viewing Party","aR":8,"nV":48}},"3":{"1":{"id":"tt4320660","pT":"Gigolo H-O-R-S-E","aR":8.6,"nV":56},"2":{"id":"tt4353848","pT":"Pleep Ploop","aR":8.5,"nV":54},"3":{"id":"tt4353856","pT":"Bangs","aR":8.3,"nV":48},"4":{"id":"tt4353862","pT":"Karaoke Bullies","aR":8.2,"nV":42},"5":{"id":"tt4432428","pT":"The in Addition Tos","aR":8.5,"nV":48},"6":{"id":"tt4459844","pT":"Lizards vs. Penguins","aR":7.5,"nV":40},"7":{"id":"tt4459848","pT":"Twins","aR":8.1,"nV":41},"8":{"id":"tt4469224","pT":"The Commonwealth Games","aR":7.8,"nV":54},"9":{"id":"tt4513388","pT":"Body Bouncers","aR":8.1,"nV":36},"10":{"id":"tt4515620","pT":"The Time of My Life","aR":8,"nV":43},"11":{"id":"tt4366152","pT":"This Has Been Such an Amazing Experience","aR":8.5,"nV":38}}}}