{"id":"tt2245310","pT":"Makers: Women Who Make America","sY":2013,"nV":144,"rM":60,"eY":null,"aR":7.5,"iA":false,"g":["Documentary"],"sI":[1,2],"eI":[1,2,3],"eM":{"1":{"1":{"id":"tt2253168","pT":"Awakening","aR":8.5,"nV":16},"2":{"id":"tt2253170","pT":"Changing the World","aR":8.1,"nV":18},"3":{"id":"tt2677030","pT":"Charting a New Course","aR":8.3,"nV":17}},"2":{"1":{"id":"tt4393086","pT":"Women in Comedy","aR":8,"nV":10},"2":{"id":"tt3975298","pT":"Women in Hollywood","aR":6.1,"nV":28},"3":{"id":"tt4107004","pT":"Women in Space","aR":7.7,"nV":12}}}}