{"id":"tt3597790","pT":"Angie Tribeca","sY":2016,"rM":30,"eY":2018,"iA":0,"aR":7,"nV":9743,"g":["Action","Comedy","Crime"],"sI":[1,2,3,4],"eI":[1,2,3,4,5,6,7,8,9,10],"eM":{"1":{"1":{"id":"tt3733914","pT":"Pilot","aR":7.3,"nV":485},"2":{"id":"tt4240004","pT":"The Wedding Planner Did It","aR":7.5,"nV":359},"3":{"id":"tt4240006","pT":"The Famous Ventriloquist Did It","aR":7.5,"nV":313},"4":{"id":"tt4240010","pT":"The Thumb Affair","aR":7.4,"nV":289},"5":{"id":"tt4241608","pT":"Commissioner Bigfish","aR":7.1,"nV":277},"6":{"id":"tt4241606","pT":"Ferret Royale","aR":7.5,"nV":267},"7":{"id":"tt4241610","pT":"Tribeca's Day Off","aR":7.6,"nV":272},"8":{"id":"tt4241612","pT":"Murder in the First Class","aR":7.2,"nV":244},"9":{"id":"tt4241614","pT":"Inside Man","aR":7.9,"nV":247},"10":{"id":"tt3899576","pT":"The One with the Bomb","aR":7.7,"nV":243}},"2":{"1":{"id":"tt5179222","pT":"Fleas Don't Kill Me","aR":7.4,"nV":216},"2":{"id":"tt5221120","pT":"Miso Dead","aR":7.3,"nV":210},"3":{"id":"tt5221122","pT":"Beach Blanket Sting-O","aR":7.5,"nV":199},"4":{"id":"tt5221124","pT":"You've Got Blackmail","aR":7.8,"nV":203},"5":{"id":"tt5221126","pT":"A Coldie But a Goodie","aR":7.1,"nV":177},"6":{"id":"tt5221130","pT":"Organ Trail","aR":7.2,"nV":178},"7":{"id":"tt5221134","pT":"Boyz II Dead","aR":7.2,"nV":179},"8":{"id":"tt5221132","pT":"The Coast Is Fear","aR":7.3,"nV":166},"9":{"id":"tt5221136","pT":"Contains Graphic Designer Violence","aR":7.5,"nV":163},"10":{"id":"tt5221138","pT":"Electoral Dysfunction","aR":7.9,"nV":169}},"3":{"1":{"id":"tt5866454","pT":"Welcome Back, Blotter","aR":8,"nV":169},"2":{"id":"tt5953358","pT":"Murder Gras","aR":7.7,"nV":151},"3":{"id":"tt5953360","pT":"Brockman Turner Overdrive","aR":7.7,"nV":138},"4":{"id":"tt5953362","pT":"Turn Me On, Geils","aR":7.8,"nV":156},"5":{"id":"tt5953364","pT":"This Sounds Unbelievable, But CSI: Miami Did It","aR":7.9,"nV":150},"6":{"id":"tt5953366","pT":"Hey, I'm Solvin' Here!","aR":7.6,"nV":147},"7":{"id":"tt5953368","pT":"License to Drill","aR":7.6,"nV":141},"8":{"id":"tt5953370","pT":"If You See Something, Solve Something","aR":7.9,"nV":139},"9":{"id":"tt5953374","pT":"Germs of Endearment","aR":7.8,"nV":132},"10":{"id":"tt5921680","pT":"Go Get 'Em, Tiger","aR":7.9,"nV":138}},"4":{"1":{"id":"tt7186704","pT":"The Force Wakes Up","aR":7.1,"nV":128},"2":{"id":"tt7734986","pT":"Glitch Perfect","aR":7.1,"nV":117},"3":{"id":"tt7735006","pT":"Joystick Luck Club","aR":7.2,"nV":104},"4":{"id":"tt7735014","pT":"Just the Fat, Ma'am","aR":7.2,"nV":104},"5":{"id":"tt7735012","pT":"Trader Foes","aR":7.5,"nV":101},"6":{"id":"tt7735016","pT":"Freezing Cold Prestige Drama","aR":7.7,"nV":107},"7":{"id":"tt7735020","pT":"Behind the Scandalabra","aR":7.3,"nV":93},"8":{"id":"tt7735026","pT":"Heading to the Legal Beagle","aR":6.9,"nV":83},"9":{"id":"tt7735028","pT":"Irrational Treasures","aR":7.5,"nV":86},"10":{"id":"tt7186730","pT":"Air Force Two","aR":7.5,"nV":90}}}}