{"id":"tt3975368","pT":"Teachers","sY":2016,"rM":30,"eY":2019,"iA":0,"aR":6.6,"nV":3679,"g":["Comedy"],"sI":[1,2,3],"eI":[1,2,3,4,5,6,7,8,9,10,11,12,13,14,15,16,17,18,19,20],"eM":{"1":{"1":{"id":"tt5120360","pT":"Pilot","aR":6.5,"nV":200},"2":{"id":"tt4549348","pT":"Picture Day","aR":7.2,"nV":142},"3":{"id":"tt4760458","pT":"Duct Duct Goose","aR":5.8,"nV":86},"4":{"id":"tt4585892","pT":"Hall of Shame","aR":5.8,"nV":74},"5":{"id":"tt4870198","pT":"Jacob","aR":5.9,"nV":77},"6":{"id":"tt4660720","pT":"Drunk Kiss","aR":5.9,"nV":81},"7":{"id":"tt5102418","pT":"Bad Tweeter","aR":5.8,"nV":69},"8":{"id":"tt4636578","pT":"Sex Ed","aR":5.8,"nV":91},"9":{"id":"tt5538892","pT":"Hot Lunch","aR":6,"nV":63},"10":{"id":"tt4718398","pT":"The Last Day","aR":5.9,"nV":68}},"2":{"1":{"id":"tt5518668","pT":"First Day Back","aR":6,"nV":86},"2":{"id":"tt6432370","pT":"Stranger Danger","aR":5.9,"nV":72},"3":{"id":"tt6035154","pT":"School Sweet School","aR":5.9,"nV":69},"4":{"id":"tt6119474","pT":"Held Back","aR":6,"nV":65},"5":{"id":"tt6065768","pT":"Snap Judgement","aR":6,"nV":82},"6":{"id":"tt6087002","pT":"Brokebitch Mountain","aR":5.9,"nV":69},"7":{"id":"tt6136014","pT":"Thirty-One and Done","aR":5.9,"nV":72},"8":{"id":"tt5962642","pT":"Getting Drilled","aR":5.8,"nV":64},"9":{"id":"tt6155908","pT":"In Security","aR":5.9,"nV":60},"10":{"id":"tt6065792","pT":"Lunchtime! The Musical","aR":6.2,"nV":67},"11":{"id":"tt6499870","pT":"Dosey Don't","aR":6,"nV":63},"12":{"id":"tt6407204","pT":"Passive Eggressive","aR":6.1,"nV":58},"13":{"id":"tt6499874","pT":"Dire Straights","aR":6,"nV":60},"14":{"id":"tt6499872","pT":"Nightmare on Fillmore Street","aR":6.1,"nV":66},"15":{"id":"tt6499882","pT":"Hot Date","aR":6,"nV":57},"16":{"id":"tt6499880","pT":"Let It Flow","aR":6.2,"nV":47},"17":{"id":"tt6499886","pT":"Third Wheel","aR":5.9,"nV":51},"18":{"id":"tt6499890","pT":"Toxic Workplace","aR":5.8,"nV":54},"19":{"id":"tt6499888","pT":"Don't Go Pranking My Heart","aR":6.2,"nV":54},"20":{"id":"tt5518670","pT":"Labor Pains","aR":6.3,"nV":60}},"3":{"1":{"id":"tt6812018","pT":"Hello, Goodbye","aR":7.7,"nV":48},"2":{"id":"tt7946248","pT":"All by Myselfie","aR":7.7,"nV":48},"3":{"id":"tt7821062","pT":"Of Lice and Men","aR":7.9,"nV":45},"4":{"id":"tt7823460","pT":"Leggo My Preggo","aR":7.9,"nV":40},"5":{"id":"tt7851114","pT":"Gender Bender","aR":8,"nV":40},"6":{"id":"tt7821064","pT":"Wake and Blake","aR":7.5,"nV":35},"7":{"id":"tt8141856","pT":"The Book Challenge","aR":7.3,"nV":37},"8":{"id":"tt7904306","pT":"For Poorer or Poorer","aR":7.8,"nV":31},"9":{"id":"tt8145182","pT":"Step by Stepsister","aR":7.9,"nV":33},"10":{"id":"tt7821066","pT":"Hot Deadly Dad","aR":7.8,"nV":35},"11":{"id":"tt8751012","pT":"Thoughts and Bears","aR":8.3,"nV":37},"12":{"id":"tt8550412","pT":"Operation Egg Drop","aR":7.8,"nV":30},"13":{"id":"tt8555048","pT":"Playing the Partum","aR":7.6,"nV":30},"14":{"id":"tt8631038","pT":"Sidelined","aR":7.7,"nV":27},"15":{"id":"tt8652618","pT":"Face Your Peers","aR":7.9,"nV":29},"16":{"id":"tt9511772","pT":"Relationslut","aR":7.7,"nV":28},"17":{"id":"tt8710708","pT":"The Final Robe","aR":8.1,"nV":33},"18":{"id":"tt8772774","pT":"The Tell-Tale Cart","aR":7.4,"nV":25},"19":{"id":"tt8784366","pT":"Teacher Depreciation Week","aR":7.6,"nV":27},"20":{"id":"tt6812022","pT":"Wedded Miss","aR":7.7,"nV":33}}}}