{"id":"tt5297548","pT":"Admirable Animation","sY":2013,"nV":141,"rM":null,"eY":null,"aR":7.1,"iA":false,"g":["Comedy"],"sI":[1,2,3],"eI":[4,5,8,19,25],"eM":{"1":{"19":{"id":"tt5778064","pT":"Jurassic Bark (Futurama)","aR":8.7,"nV":10}},"2":{"4":{"id":"tt5874408","pT":"April 9th (Arthur)","aR":6.5,"nV":7},"8":{"id":"tt5937262","pT":"It's a Spongebob Christmas (Spongebob)","aR":6.8,"nV":7},"19":{"id":"tt6003812","pT":"Burritor (We Bare Bears)","aR":8,"nV":7},"25":{"id":"tt6016492","pT":"TTG vs PPG","aR":8,"nV":8}},"3":{"5":{"id":"tt7420582","pT":"Mimic Madness","aR":6.6,"nV":5}}}}