{"id":"tt7056766","pT":"Reunited Worlds","sY":2017,"nV":413,"rM":null,"eY":2017,"aR":7.2,"iA":false,"g":["Fantasy","Romance"],"sI":[1],"eI":[1,2,3,4,5,6,7,8,9,10,11,12,27],"eM":{"1":{"1":{"id":"tt7157694","pT":"The Return","aR":8.4,"nV":13},"2":{"id":"tt7157696","pT":"The Accident","aR":8.4,"nV":8},"3":{"id":"tt7157700","pT":"How Is He Alive?","aR":8.2,"nV":7},"4":{"id":"tt7157704","pT":"Endless Confusion","aR":8.5,"nV":7},"5":{"id":"tt7177892","pT":"Figuring Out the Present","aR":8.5,"nV":7},"6":{"id":"tt7177894","pT":"Putting the Pieces Back Together","aR":8.5,"nV":7},"7":{"id":"tt7177900","pT":"In His Place","aR":8.6,"nV":6},"8":{"id":"tt7177902","pT":"The Meaning of Family","aR":8.8,"nV":6},"9":{"id":"tt7185914","pT":"You Are Not My Brother","aR":8.6,"nV":6},"10":{"id":"tt7185926","pT":"Living Your Dream","aR":8.6,"nV":6},"11":{"id":"tt7185928","pT":"Who Killed Hae Sung?","aR":8.6,"nV":6},"12":{"id":"tt7185932","pT":"The Fireworks","aR":9,"nV":6},"27":{"id":"tt7268652","pT":"The Mysterious Ties","aR":9,"nV":6}}}}