{"id":"tt8726102","pT":"Thai Cave Rescue","sY":2022,"rM":60,"eY":2022,"iA":0,"aR":7.8,"nV":2525,"g":["Adventure","Drama","Thriller"],"sI":[1],"eI":[1,2,3,4,5,6],"eM":{"1":{"1":{"id":"tt15340490","pT":"The Legend of Tham Luang","aR":7.5,"nV":96},"2":{"id":"tt21050062","pT":"To Not Offend the Gods","aR":7.8,"nV":89},"3":{"id":"tt21050082","pT":"The Princess' Chalice","aR":7.7,"nV":87},"4":{"id":"tt21048302","pT":"Lucky Baht","aR":8.1,"nV":84},"5":{"id":"tt21050094","pT":"The Parable of Kisa Gotami","aR":8.1,"nV":87},"6":{"id":"tt19889964","pT":"Moo Pa","aR":8.2,"nV":86}}}}