{"id":"tt9059350","pT":"Warrior Nun","sY":2020,"rM":null,"eY":2022,"iA":0,"aR":7,"nV":56326,"g":["Action","Drama","Fantasy"],"sI":[1,2],"eI":[1,2,3,4,5,6,7,8,9,10],"eM":{"1":{"1":{"id":"tt9913754","pT":"Psalm 46:5","aR":7.3,"nV":5416},"2":{"id":"tt10102646","pT":"Proverbs 31:25","aR":7.3,"nV":4957},"3":{"id":"tt10102648","pT":"Ephesians 6:11","aR":7.4,"nV":4852},"4":{"id":"tt10102652","pT":"Ecclesiasticus 26:9-10","aR":7.5,"nV":4736},"5":{"id":"tt10102654","pT":"Matthew 7:13","aR":7.6,"nV":4717},"6":{"id":"tt10102658","pT":"Isaiah 30:20-21","aR":7.6,"nV":4741},"7":{"id":"tt10102660","pT":"Ephesians 4:22-24","aR":7.7,"nV":4670},"8":{"id":"tt10102666","pT":"Proverbs 14:1","aR":7.7,"nV":4695},"9":{"id":"tt10102668","pT":"2 Corinthians 10:4","aR":8.1,"nV":4765},"10":{"id":"tt10102670","pT":"Revelation 2:10","aR":8.2,"nV":4972}},"2":{"1":{"id":"tt12923736","pT":"Galatians 6:4-5","aR":8.2,"nV":5823},"2":{"id":"tt23555830","pT":"Colossians 3:9-10","aR":8.1,"nV":5476},"3":{"id":"tt23556154","pT":"Luke 8:17","aR":8.3,"nV":5467},"4":{"id":"tt23556156","pT":"Corinthians 10:20-21","aR":8.3,"nV":5521},"5":{"id":"tt23556158","pT":"Mark 10:45","aR":8.5,"nV":5451},"6":{"id":"tt23556160","pT":"Isaiah 40:31","aR":8.5,"nV":5671},"7":{"id":"tt23556164","pT":"Psalms 116:15","aR":8.4,"nV":5514},"8":{"id":"tt23556166","pT":"Jeremiah 29:13","aR":8.6,"nV":6439}}}}